{
  "timestamp": "2025-08-03T14:39:47",
  "rps": 3,
  "duration_sec": 30,
  "requests_sent": 300,
  "successful": 300,
  "errors": 0,
  "avg_latency_ms": 134.25,
  "p95_latency_ms": 193,
  "p99_latency_ms": 216,
  "cv_latency": 26.74,
  "raw_output": "\u26a1 \u041d\u0430\u0447\u0430\u043b\u043e stress-\u0442\u0435\u0441\u0442\u0430: 5 RPS \u043d\u0430 60 \u0441\u0435\u043a\u0443\u043d\u0434\n[/run_bash] 200 - 62ms\n[/agent/status] 200 - 82ms\n[/agent/status] 200 - 83ms\n[/agent/status] 200 - 93ms\n[/agent/status] 200 - 117ms\n[/run_bash] 200 - 136ms\n[/run_bash] 200 - 163ms\n[/agent/pipeline] 200 - 178ms\n[/agent/pipeline] 200 - 197ms\n[/agent/pipeline] 200 - 217ms\n[/agent/status] 200 - 96ms\n[/run_bash] 200 - 122ms\n[/agent/status] 200 - 125ms\n[/agent/pipeline] 200 - 138ms\n[/run_bash] 200 - 166ms\n[/agent/status] 200 - 74ms\n[/run_bash] 200 - 95ms\n[/agent/pipeline] 200 - 108ms\n[/agent/pipeline] 200 - 139ms\n[/run_bash] 200 - 150ms\n[/agent/status] 200 - 79ms\n[/run_bash] 200 - 116ms\n[/run_bash] 200 - 126ms\n[/agent/pipeline] 200 - 141ms\n[/agent/pipeline] 200 - 155ms\n[/run_bash] 200 - 94ms\n[/run_bash] 200 - 101ms\n[/agent/status] 200 - 121ms\n[/agent/status] 200 - 133ms\n[/agent/status] 200 - 171ms\n[/agent/status] 200 - 69ms\n[/agent/pipeline] 200 - 109ms\n[/run_bash] 200 - 114ms\n[/agent/pipeline] 200 - 132ms\n[/agent/pipeline] 200 - 145ms\n[/run_bash] 200 - 81ms\n[/run_bash] 200 - 89ms\n[/run_bash] 200 - 111ms\n[/run_bash] 200 - 121ms\n[/run_bash] 200 - 143ms\n[/agent/status] 200 - 62ms\n[/agent/status] 200 - 78ms\n[/run_bash] 200 - 92ms\n[/agent/pipeline] 200 - 103ms\n[/agent/pipeline] 200 - 120ms\n[/agent/status] 200 - 46ms\n[/agent/status] 200 - 73ms\n[/run_bash] 200 - 108ms\n[/run_bash] 200 - 115ms\n[/agent/pipeline] 200 - 127ms\n[/agent/status] 200 - 73ms\n[/agent/pipeline] 200 - 100ms\n[/run_bash] 200 - 115ms\n[/agent/pipeline] 200 - 135ms\n[/agent/pipeline] 200 - 154ms\n[/agent/status] 200 - 88ms\n[/agent/status] 200 - 84ms\n[/agent/pipeline] 200 - 132ms\n[/agent/pipeline] 200 - 146ms\n[/agent/pipeline] 200 - 163ms\n[/agent/status] 200 - 64ms\n[/run_bash] 200 - 97ms\n[/agent/pipeline] 200 - 127ms\n[/agent/pipeline] 200 - 144ms\n[/agent/pipeline] 200 - 159ms\n[/agent/status] 200 - 98ms\n[/run_bash] 200 - 106ms\n[/agent/pipeline] 200 - 126ms\n[/agent/pipeline] 200 - 147ms\n[/run_bash] 200 - 157ms\n[/agent/status] 200 - 116ms\n[/agent/pipeline] 200 - 141ms\n[/run_bash] 200 - 159ms\n[/agent/pipeline] 200 - 171ms\n[/run_bash] 200 - 182ms\n[/run_bash] 200 - 129ms\n[/run_bash] 200 - 143ms\n[/agent/pipeline] 200 - 154ms\n[/agent/pipeline] 200 - 176ms\n[/agent/status] 200 - 185ms\n[/agent/status] 200 - 101ms\n[/agent/status] 200 - 118ms\n[/agent/status] 200 - 131ms\n[/agent/pipeline] 200 - 157ms\n[/run_bash] 200 - 166ms\n[/agent/status] 200 - 119ms\n[/agent/status] 200 - 123ms\n[/run_bash] 200 - 144ms\n[/run_bash] 200 - 153ms\n[/agent/status] 200 - 156ms\n[/agent/status] 200 - 112ms\n[/run_bash] 200 - 146ms\n[/run_bash] 200 - 150ms\n[/agent/pipeline] 200 - 170ms\n[/agent/status] 200 - 179ms\n[/agent/status] 200 - 85ms\n[/run_bash] 200 - 104ms\n[/run_bash] 200 - 117ms\n[/agent/status] 200 - 130ms\n[/run_bash] 200 - 157ms\n[/agent/status] 200 - 113ms\n[/agent/status] 200 - 133ms\n[/run_bash] 200 - 162ms\n[/agent/pipeline] 200 - 170ms\n[/agent/pipeline] 200 - 199ms\n[/agent/status] 200 - 122ms\n[/run_bash] 200 - 145ms\n[/agent/pipeline] 200 - 167ms\n[/agent/pipeline] 200 - 184ms\n[/agent/pipeline] 200 - 198ms\n[/agent/status] 200 - 130ms\n[/agent/status] 200 - 152ms\n[/agent/pipeline] 200 - 158ms\n[/agent/pipeline] 200 - 190ms\n[/run_bash] 200 - 201ms\n[/agent/status] 200 - 99ms\n[/agent/status] 200 - 110ms\n[/run_bash] 200 - 125ms\n[/agent/pipeline] 200 - 139ms\n[/agent/status] 200 - 153ms\n[/agent/status] 200 - 109ms\n[/agent/pipeline] 200 - 127ms\n[/run_bash] 200 - 134ms\n[/agent/pipeline] 200 - 149ms\n[/agent/pipeline] 200 - 174ms\n[/agent/status] 200 - 103ms\n[/agent/status] 200 - 127ms\n[/agent/pipeline] 200 - 147ms\n[/run_bash] 200 - 168ms\n[/agent/pipeline] 200 - 179ms\n[/agent/status] 200 - 100ms\n[/agent/status] 200 - 127ms\n[/agent/status] 200 - 131ms\n[/agent/pipeline] 200 - 161ms\n[/agent/pipeline] 200 - 173ms\n[/run_bash] 200 - 75ms\n[/agent/status] 200 - 82ms\n[/agent/pipeline] 200 - 100ms\n[/run_bash] 200 - 106ms\n[/agent/pipeline] 200 - 117ms\n[/agent/status] 200 - 131ms\n[/run_bash] 200 - 159ms\n[/agent/pipeline] 200 - 171ms\n[/agent/pipeline] 200 - 186ms\n[/agent/pipeline] 200 - 202ms\n[/agent/status] 200 - 102ms\n[/agent/status] 200 - 112ms\n[/run_bash] 200 - 136ms\n[/agent/pipeline] 200 - 155ms\n[/agent/pipeline] 200 - 179ms\n[/agent/status] 200 - 103ms\n[/run_bash] 200 - 112ms\n[/run_bash] 200 - 132ms\n[/run_bash] 200 - 153ms\n[/agent/pipeline] 200 - 176ms\n[/run_bash] 200 - 107ms\n[/run_bash] 200 - 124ms\n[/run_bash] 200 - 130ms\n[/run_bash] 200 - 149ms\n[/agent/pipeline] 200 - 168ms\n[/agent/status] 200 - 81ms\n[/agent/status] 200 - 98ms\n[/agent/status] 200 - 107ms\n[/agent/pipeline] 200 - 117ms\n[/agent/status] 200 - 157ms\n[/agent/status] 200 - 88ms\n[/agent/status] 200 - 118ms\n[/agent/status] 200 - 133ms\n[/agent/pipeline] 200 - 148ms\n[/agent/status] 200 - 184ms\n[/agent/status] 200 - 81ms\n[/agent/pipeline] 200 - 100ms\n[/run_bash] 200 - 116ms\n[/agent/pipeline] 200 - 130ms\n[/agent/pipeline] 200 - 149ms\n[/agent/status] 200 - 121ms\n[/run_bash] 200 - 151ms\n[/agent/pipeline] 200 - 162ms\n[/agent/pipeline] 200 - 183ms\n[/agent/pipeline] 200 - 190ms\n[/run_bash] 200 - 114ms\n[/agent/status] 200 - 125ms\n[/run_bash] 200 - 173ms\n[/run_bash] 200 - 185ms\n[/run_bash] 200 - 218ms\n[/agent/status] 200 - 106ms\n[/run_bash] 200 - 129ms\n[/agent/pipeline] 200 - 146ms\n[/agent/status] 200 - 180ms\n[/run_bash] 200 - 210ms\n[/agent/status] 200 - 101ms\n[/run_bash] 200 - 140ms\n[/agent/pipeline] 200 - 169ms\n[/run_bash] 200 - 190ms\n[/run_bash] 200 - 216ms\n[/agent/status] 200 - 112ms\n[/agent/status] 200 - 123ms\n[/run_bash] 200 - 173ms\n[/agent/pipeline] 200 - 188ms\n[/agent/pipeline] 200 - 200ms\n[/agent/status] 200 - 105ms\n[/run_bash] 200 - 117ms\n[/agent/pipeline] 200 - 133ms\n[/run_bash] 200 - 151ms\n[/run_bash] 200 - 175ms\n[/agent/status] 200 - 101ms\n[/run_bash] 200 - 126ms\n[/agent/pipeline] 200 - 144ms\n[/agent/status] 200 - 152ms\n[/run_bash] 200 - 166ms\n[/agent/status] 200 - 95ms\n[/agent/status] 200 - 113ms\n[/agent/status] 200 - 130ms\n[/run_bash] 200 - 143ms\n[/run_bash] 200 - 179ms\n[/agent/status] 200 - 115ms\n[/run_bash] 200 - 128ms\n[/agent/pipeline] 200 - 161ms\n[/agent/pipeline] 200 - 169ms\n[/agent/pipeline] 200 - 186ms\n[/agent/status] 200 - 58ms\n[/run_bash] 200 - 71ms\n[/agent/status] 200 - 80ms\n[/agent/pipeline] 200 - 95ms\n[/agent/status] 200 - 107ms\n[/agent/status] 200 - 109ms\n[/agent/status] 200 - 126ms\n[/agent/pipeline] 200 - 153ms\n[/agent/pipeline] 200 - 164ms\n[/agent/pipeline] 200 - 182ms\n[/agent/status] 200 - 84ms\n[/run_bash] 200 - 99ms\n[/agent/pipeline] 200 - 107ms\n[/agent/pipeline] 200 - 137ms\n[/agent/pipeline] 200 - 154ms\n[/agent/status] 200 - 122ms\n[/agent/pipeline] 200 - 152ms\n[/run_bash] 200 - 168ms\n[/run_bash] 200 - 173ms\n[/agent/pipeline] 200 - 192ms\n[/agent/status] 200 - 102ms\n[/agent/status] 200 - 117ms\n[/run_bash] 200 - 133ms\n[/agent/pipeline] 200 - 141ms\n[/run_bash] 200 - 170ms\n[/agent/status] 200 - 70ms\n[/run_bash] 200 - 87ms\n[/agent/pipeline] 200 - 103ms\n[/agent/status] 200 - 119ms\n[/agent/pipeline] 200 - 132ms\n[/agent/status] 200 - 91ms\n[/agent/status] 200 - 115ms\n[/agent/status] 200 - 122ms\n[/agent/status] 200 - 141ms\n[/agent/pipeline] 200 - 149ms\n[/agent/status] 200 - 129ms\n[/run_bash] 200 - 150ms\n[/run_bash] 200 - 159ms\n[/run_bash] 200 - 172ms\n[/agent/pipeline] 200 - 203ms\n[/agent/status] 200 - 120ms\n[/agent/status] 200 - 141ms\n[/agent/pipeline] 200 - 156ms\n[/agent/pipeline] 200 - 171ms\n[/agent/pipeline] 200 - 197ms\n[/agent/status] 200 - 71ms\n[/agent/status] 200 - 104ms\n[/agent/status] 200 - 117ms\n[/agent/pipeline] 200 - 166ms\n[/run_bash] 200 - 178ms\n[/agent/status] 200 - 79ms\n[/agent/status] 200 - 102ms\n[/run_bash] 200 - 127ms\n[/run_bash] 200 - 147ms\n[/agent/pipeline] 200 - 164ms\n[/agent/pipeline] 200 - 115ms\n[/run_bash] 200 - 116ms\n[/agent/pipeline] 200 - 136ms\n[/agent/pipeline] 200 - 154ms\n[/run_bash] 200 - 188ms\n[/agent/pipeline] 200 - 124ms\n[/agent/pipeline] 200 - 139ms\n[/run_bash] 200 - 152ms\n[/agent/pipeline] 200 - 175ms\n[/run_bash] 200 - 193ms\n[/agent/status] 200 - 38ms\n[/agent/status] 200 - 50ms\n[/agent/status] 200 - 67ms\n[/agent/status] 200 - 85ms\n[/agent/status] 200 - 100ms\n[/agent/status] 200 - 131ms\n[/run_bash] 200 - 151ms\n[/agent/pipeline] 200 - 180ms\n[/agent/pipeline] 200 - 201ms\n[/agent/pipeline] 200 - 208ms\n[/agent/status] 200 - 102ms\n[/agent/pipeline] 200 - 146ms\n[/agent/pipeline] 200 - 159ms\n[/agent/pipeline] 200 - 168ms\n[/agent/pipeline] 200 - 188ms",
  "returncode": 0
}